cerebrate_sdk/__init__.py
cerebrate_sdk/error.py
cerebrate_sdk/main.py
cerebrate_sdk-0.2.1.dist-info/WHEEL
cerebrate_sdk-0.2.1.dist-info/METADATA
cerebrate_sdk-0.2.1.dist-info/RECORD
