Metadata-Version: 2.1
Name: cerebrate-sdk
Version: 0.2.1
Summary: Cerebrate SDK
Author: Cerebrate AI
Author-email: admin@cerebrate.ai
Requires-Python: >=3.5,<4.0
Classifier: Programming Language :: Python :: 3
Classifier: Programming Language :: Python :: 3.5
Classifier: Programming Language :: Python :: 3.6
Classifier: Programming Language :: Python :: 3.7
Classifier: Programming Language :: Python :: 3.8
Classifier: Programming Language :: Python :: 3.9
Requires-Dist: requests
